{
  "blogPosts": [
    {
      "id": "welcome",
      "metadata": {
        "permalink": "/physical-ai-book/blog/welcome",
        "editUrl": "https://github.com/your-username/physical-ai-book/tree/main/website/blog/2025-01-01-welcome.md",
        "source": "@site/blog/2025-01-01-welcome.md",
        "title": "Welcome to the Physical AI Book",
        "description": "Welcome to the Physical AI Book! This blog will feature updates, insights, and additional content related to the intersection of physical systems and artificial intelligence.",
        "date": "2025-01-01T00:00:00.000Z",
        "formattedDate": "January 1, 2025",
        "tags": [
          {
            "label": "physical-ai",
            "permalink": "/physical-ai-book/blog/tags/physical-ai"
          },
          {
            "label": "docusaurus",
            "permalink": "/physical-ai-book/blog/tags/docusaurus"
          }
        ],
        "readingTime": 0.465,
        "hasTruncateMarker": true,
        "authors": [
          {
            "name": "Sébastien Lorber",
            "title": "Docusaurus maintainer",
            "url": "https://sebastienlorber.com",
            "imageURL": "https://github.com/slorber.png",
            "key": "slorber"
          }
        ],
        "frontMatter": {
          "slug": "welcome",
          "title": "Welcome to the Physical AI Book",
          "authors": [
            "slorber"
          ],
          "tags": [
            "physical-ai",
            "docusaurus"
          ]
        },
        "unlisted": false
      },
      "content": "Welcome to the Physical AI Book! This blog will feature updates, insights, and additional content related to the intersection of physical systems and artificial intelligence.\n\n<!-- truncate -->\n\nThis project aims to provide comprehensive coverage of Physical AI concepts, from foundational principles to advanced applications. We'll explore how AI systems interact with the physical world through sensors, actuators, and control systems.\n\nStay tuned for more posts covering topics like:\n- Advanced robotics applications\n- Sensor fusion techniques\n- Control theory in AI systems\n- Safety considerations in Physical AI\n- Real-world case studies"
    }
  ]
}